luckypot/__init__.py
luckypot/app.py
luckypot/assets.py
luckypot/common_objects.py
luckypot/constants.py
luckypot/debug.py
luckypot/examples/__init__.py
luckypot/examples/__main__.py
luckypot/examples/assets/animations/bird.json
luckypot/examples/assets/images/ByCozyFractal.png
luckypot/examples/assets/images/bird.png
luckypot/examples/assets/images/tiles.png
luckypot/examples/assets/sfx/back.wav
luckypot/examples/sunset.py
luckypot/gfx.py
luckypot/object.py
luckypot/particles.py
luckypot/pygame_input.py
luckypot/screen.py
luckypot/settings.py
luckypot/simple_ui.py
luckypot/state.py
luckypot/state_machine.py
luckypot/state_transitions.py
luckypot/utils.py
luckypot-0.1.1.dist-info/METADATA
luckypot-0.1.1.dist-info/WHEEL
luckypot-0.1.1.dist-info/RECORD
