Metadata-Version: 2.1
Name: luckypot
Version: 0.1.1
Summary: Another pygame engine. It might be what you need, if you're lucky to be called Diego.
License: GPL-3.0
Author: ddorn
Author-email: diego.dorn@free.fr
Requires-Python: >=3.9,<4.0
Classifier: License :: OSI Approved :: GNU General Public License v3 (GPLv3)
Classifier: Programming Language :: Python :: 3
Classifier: Programming Language :: Python :: 3.9
Classifier: Programming Language :: Python :: 3.10
Classifier: Programming Language :: Python :: 3.11
Classifier: Programming Language :: Python :: 3.12
Requires-Dist: pygame-ce (>=2.5.0,<3.0.0)
